odoo/addons/stock_landed_costs_priority/README.rst
odoo/addons/stock_landed_costs_priority/__init__.py
odoo/addons/stock_landed_costs_priority/__manifest__.py
odoo/addons/stock_landed_costs_priority/i18n/es.po
odoo/addons/stock_landed_costs_priority/i18n/it.po
odoo/addons/stock_landed_costs_priority/i18n/pt.po
odoo/addons/stock_landed_costs_priority/i18n/pt_BR.po
odoo/addons/stock_landed_costs_priority/i18n/stock_landed_costs_priority.pot
odoo/addons/stock_landed_costs_priority/models/__init__.py
odoo/addons/stock_landed_costs_priority/models/stock_landed_cost.py
odoo/addons/stock_landed_costs_priority/readme/CONTRIBUTORS.md
odoo/addons/stock_landed_costs_priority/readme/DESCRIPTION.md
odoo/addons/stock_landed_costs_priority/static/description/icon.png
odoo/addons/stock_landed_costs_priority/static/description/index.html
odoo/addons/stock_landed_costs_priority/views/stock_landed_cost_views.xml
odoo_addon_stock_landed_costs_priority-18.0.1.0.0.6.dist-info/METADATA
odoo_addon_stock_landed_costs_priority-18.0.1.0.0.6.dist-info/WHEEL
odoo_addon_stock_landed_costs_priority-18.0.1.0.0.6.dist-info/top_level.txt
odoo_addon_stock_landed_costs_priority-18.0.1.0.0.6.dist-info/RECORD
